backend/__init__.py
backend/server.py
backend/utils.py
backend/websocket_manager.py
backend/report_type/__init__.py
backend/report_type/basic_report/__init__.py
backend/report_type/basic_report/basic_report.py
backend/report_type/detailed_report/__init__.py
backend/report_type/detailed_report/detailed_report.py
researcher/__init__.py
researcher/main.py
researcher/config/__init__.py
researcher/config/config.py
researcher/context/__init__.py
researcher/context/compression.py
researcher/context/retriever.py
researcher/llm_provider/__init__.py
researcher/llm_provider/azureopenai/__init__.py
researcher/llm_provider/azureopenai/azureopenai.py
researcher/llm_provider/google/__init__.py
researcher/llm_provider/google/google.py
researcher/llm_provider/groq/__init__.py
researcher/llm_provider/groq/groq.py
researcher/llm_provider/openai/__init__.py
researcher/llm_provider/openai/openai.py
researcher/master/__init__.py
researcher/master/agent.py
researcher/master/functions.py
researcher/master/prompts.py
researcher/memory/__init__.py
researcher/memory/embeddings.py
researcher/retrievers/__init__.py
researcher/retrievers/bing/__init__.py
researcher/retrievers/bing/bing.py
researcher/retrievers/duckduckgo/__init__.py
researcher/retrievers/duckduckgo/duckduckgo.py
researcher/retrievers/google/__init__.py
researcher/retrievers/google/google.py
researcher/retrievers/searx/__init__.py
researcher/retrievers/searx/searx.py
researcher/retrievers/serpapi/__init__.py
researcher/retrievers/serpapi/serpapi.py
researcher/retrievers/serper/__init__.py
researcher/retrievers/serper/serper.py
researcher/retrievers/tavily_news/__init__.py
researcher/retrievers/tavily_news/tavily_news.py
researcher/retrievers/tavily_search/__init__.py
researcher/retrievers/tavily_search/tavily_search.py
researcher/scraper/__init__.py
researcher/scraper/scraper.py
researcher/scraper/arxiv/__init__.py
researcher/scraper/arxiv/arxiv.py
researcher/scraper/beautiful_soup/__init__.py
Researcher-0.4.3.dist-info/LICENSE
Researcher-0.4.3.dist-info/METADATA
Researcher-0.4.3.dist-info/WHEEL
Researcher-0.4.3.dist-info/top_level.txt
Researcher-0.4.3.dist-info/RECORD
