Metadata-Version: 2.1
Name: Researcher
Version: 0.4.3
Summary: Llama Researcher is an autonomous agent designed for comprehensive online research on a variety of tasks.
Home-page: https://github.com/saeid976/Llama-Researcher.git
Author: saeid
Author-email: saeid2015dr@gmail.com
License: MIT
Classifier: License :: OSI Approved :: MIT License
Classifier: Intended Audience :: Developers
Classifier: Intended Audience :: Education
Classifier: Intended Audience :: Science/Research
Classifier: Programming Language :: Python :: 3.11
Classifier: Programming Language :: Python :: 3.12
Classifier: Topic :: Scientific/Engineering :: Artificial Intelligence
License-File: LICENSE
Requires-Dist: beautifulsoup4
Requires-Dist: colorama
Requires-Dist: duckduckgo-search
Requires-Dist: md2pdf
Requires-Dist: playwright
Requires-Dist: openai
Requires-Dist: python-dotenv
Requires-Dist: pyyaml
Requires-Dist: uvicorn
Requires-Dist: pydantic
Requires-Dist: fastapi
Requires-Dist: python-multipart
Requires-Dist: markdown
Requires-Dist: langchain
Requires-Dist: tavily-python
Requires-Dist: arxiv
Requires-Dist: PyMuPDF
Requires-Dist: requests
Requires-Dist: jinja2
Requires-Dist: aiofiles
Requires-Dist: newspaper3k
Requires-Dist: langchain-community
Requires-Dist: SQLAlchemy
Requires-Dist: langchain-openai
Requires-Dist: langchain-groq
Requires-Dist: mistune
Requires-Dist: python-docx
Requires-Dist: htmldocx
Requires-Dist: langchain-google-genai
Requires-Dist: lxml[html_clean]
Requires-Dist: websockets
